<annotation><filename>0d57d53254bd9689.jpg</filename><folder>images</folder><size><width>1024</width><height>640</height><depth>3</depth></size><object><name>Person</name><pose>Unspecified</pose><truncated>0</truncated><difficult>0</difficult><bndbox><xmin>0.0</xmin><ymin>0.0</ymin><xmax>89.824256</xmax><ymax>47.268480000000004</ymax></bndbox></object><object><name>Person</name><pose>Unspecified</pose><truncated>0</truncated><difficult>0</difficult><bndbox><xmin>363.05510400000003</xmin><ymin>0.0</ymin><xmax>435.579904</xmax><ymax>205.02528</ymax></bndbox></object></annotation>