<annotation><filename>2b830ef5fcf52c86.jpg</filename><folder>images</folder><size><width>1024</width><height>627</height><depth>3</depth></size><object><name>Person</name><pose>Unspecified</pose><truncated>0</truncated><difficult>0</difficult><bndbox><xmin>0.580608</xmin><ymin>261.83770799999996</ymin><xmax>999.254016</xmax><ymax>571.845945</ymax></bndbox></object><object><name>Person</name><pose>Unspecified</pose><truncated>0</truncated><difficult>0</difficult><bndbox><xmin>570.397696</xmin><ymin>448.970247</ymin><xmax>733.708288</xmax><ymax>570.515451</ymax></bndbox></object></annotation>