<annotation><filename>83ab987502a09a6b.jpg</filename><folder>images</folder><size><width>1024</width><height>674</height><depth>3</depth></size><object><name>Person</name><pose>Unspecified</pose><truncated>0</truncated><difficult>0</difficult><bndbox><xmin>81.87392</xmin><ymin>18.78438</ymin><xmax>1004.050432</xmax><ymax>585.720828</ymax></bndbox></object><object><name>Person</name><pose>Unspecified</pose><truncated>0</truncated><difficult>0</difficult><bndbox><xmin>153.663488</xmin><ymin>28.135455999999998</ymin><xmax>463.0016</xmax><ymax>228.02498400000002</ymax></bndbox></object><object><name>Person</name><pose>Unspecified</pose><truncated>0</truncated><difficult>0</difficult><bndbox><xmin>425.063424</xmin><ymin>0.0</ymin><xmax>983.622656</xmax><ymax>163.14844</ymax></bndbox></object></annotation>