<annotation><filename>9625acfe5037f557.jpg</filename><folder>images</folder><size><width>1024</width><height>745</height><depth>3</depth></size><object><name>Person</name><pose>Unspecified</pose><truncated>0</truncated><difficult>0</difficult><bndbox><xmin>154.724352</xmin><ymin>95.09999499999999</ymin><xmax>913.15712</xmax><ymax>716.01354</ymax></bndbox></object><object><name>Person</name><pose>Unspecified</pose><truncated>0</truncated><difficult>0</difficult><bndbox><xmin>333.032448</xmin><ymin>299.59281</ymin><xmax>700.059648</xmax><ymax>697.959955</ymax></bndbox></object></annotation>