<annotation><filename>9c2055d949287e99.jpg</filename><folder>images</folder><size><width>1024</width><height>683</height><depth>3</depth></size><object><name>Person</name><pose>Unspecified</pose><truncated>0</truncated><difficult>0</difficult><bndbox><xmin>352.565248</xmin><ymin>192.50286699999998</ymin><xmax>404.041728</xmax><ymax>251.163688</ymax></bndbox></object><object><name>Person</name><pose>Unspecified</pose><truncated>0</truncated><difficult>0</difficult><bndbox><xmin>370.315264</xmin><ymin>202.576434</ymin><xmax>426.525696</xmax><ymax>284.93803799999995</ymax></bndbox></object><object><name>Person</name><pose>Unspecified</pose><truncated>0</truncated><difficult>0</difficult><bndbox><xmin>398.12505600000003</xmin><ymin>210.27930800000001</ymin><xmax>467.352576</xmax><ymax>280.790179</ymax></bndbox></object></annotation>