<annotation><filename>a6cc6313fbdaef76.jpg</filename><folder>images</folder><size><width>1024</width><height>683</height><depth>3</depth></size><object><name>Person</name><pose>Unspecified</pose><truncated>0</truncated><difficult>0</difficult><bndbox><xmin>16.317439999999998</xmin><ymin>244.376034</ymin><xmax>55.276543999999994</xmax><ymax>448.648357</ymax></bndbox></object><object><name>Person</name><pose>Unspecified</pose><truncated>0</truncated><difficult>0</difficult><bndbox><xmin>32.911359999999995</xmin><ymin>242.932172</ymin><xmax>97.842176</xmax><ymax>461.641066</ymax></bndbox></object><object><name>Person</name><pose>Unspecified</pose><truncated>0</truncated><difficult>0</difficult><bndbox><xmin>81.24928</xmin><ymin>253.759771</ymin><xmax>103.614464</xmax><ymax>320.887743</ymax></bndbox></object><object><name>Person</name><pose>Unspecified</pose><truncated>0</truncated><difficult>0</difficult><bndbox><xmin>107.220992</xmin><ymin>249.42886800000002</ymin><xmax>126.700544</xmax><ymax>326.662508</ymax></bndbox></object><object><name>Person</name><pose>Unspecified</pose><truncated>0</truncated><difficult>0</difficult><bndbox><xmin>131.030016</xmin><ymin>268.195659</ymin><xmax>144.73728</xmax><ymax>321.609674</ymax></bndbox></object><object><name>Person</name><pose>Unspecified</pose><truncated>0</truncated><difficult>0</difficult><bndbox><xmin>141.851648</xmin><ymin>263.864756</ymin><xmax>151.95136000000002</xmax><ymax>320.887743</ymax></bndbox></object><object><name>Person</name><pose>Unspecified</pose><truncated>0</truncated><difficult>0</difficult><bndbox><xmin>185.860096</xmin><ymin>245.09796500000002</ymin><xmax>209.668096</xmax><ymax>318.72263300000003</ymax></bndbox></object><object><name>Person</name><pose>Unspecified</pose><truncated>0</truncated><difficult>0</difficult><bndbox><xmin>252.23475200000001</xmin><ymin>232.827187</ymin><xmax>309.22956800000003</xmax><ymax>423.38487</ymax></bndbox></object><object><name>Person</name><pose>Unspecified</pose><truncated>0</truncated><difficult>0</difficult><bndbox><xmin>304.90112</xmin><ymin>214.78164399999997</ymin><xmax>369.11104</xmax><ymax>421.21975999999995</ymax></bndbox></object><object><name>Person</name><pose>Unspecified</pose><truncated>0</truncated><difficult>0</difficult><bndbox><xmin>316.444672</xmin><ymin>328.827618</ymin><xmax>483.822592</xmax><ymax>515.777012</ymax></bndbox></object><object><name>Person</name><pose>Unspecified</pose><truncated>0</truncated><difficult>0</difficult><bndbox><xmin>346.745856</xmin><ymin>246.541144</ymin><xmax>410.95577599999996</xmax><ymax>427.71577300000007</ymax></bndbox></object><object><name>Person</name><pose>Unspecified</pose><truncated>0</truncated><difficult>0</difficult><bndbox><xmin>454.964224</xmin><ymin>282.63223</ymin><xmax>574.7261440000001</xmax><ymax>602.393706</ymax></bndbox></object><object><name>Person</name><pose>Unspecified</pose><truncated>0</truncated><difficult>0</difficult><bndbox><xmin>535.768064</xmin><ymin>247.985006</ymin><xmax>595.648512</xmax><ymax>367.083814</ymax></bndbox></object><object><name>Person</name><pose>Unspecified</pose><truncated>0</truncated><difficult>0</difficult><bndbox><xmin>646.151168</xmin><ymin>202.510866</ymin><xmax>700.981248</xmax><ymax>393.79048000000006</ymax></bndbox></object><object><name>Person</name><pose>Unspecified</pose><truncated>0</truncated><difficult>0</difficult><bndbox><xmin>699.5384320000001</xmin><ymin>223.44344999999998</ymin><xmax>770.241536</xmax><ymax>387.294467</ymax></bndbox></object><object><name>Person</name><pose>Unspecified</pose><truncated>0</truncated><difficult>0</difficult><bndbox><xmin>752.92672</xmin><ymin>224.16538100000002</ymin><xmax>785.391616</xmax><ymax>306.451855</ymax></bndbox></object><object><name>Person</name><pose>Unspecified</pose><truncated>0</truncated><difficult>0</difficult><bndbox><xmin>781.063168</xmin><ymin>185.90918499999998</ymin><xmax>833.729536</xmax><ymax>379.354592</ymax></bndbox></object><object><name>Person</name><pose>Unspecified</pose><truncated>0</truncated><difficult>0</difficult><bndbox><xmin>892.8890880000001</xmin><ymin>283.353478</ymin><xmax>1024.0</xmax><ymax>665.191458</ymax></bndbox></object><object><name>Person</name><pose>Unspecified</pose><truncated>0</truncated><difficult>0</difficult><bndbox><xmin>894.3319039999999</xmin><ymin>216.947437</ymin><xmax>926.076928</xmax><ymax>273.248493</ymax></bndbox></object><object><name>Person</name><pose>Unspecified</pose><truncated>0</truncated><difficult>0</difficult><bndbox><xmin>942.6698240000001</xmin><ymin>202.510866</ymin><xmax>970.8072960000001</xmax><ymax>273.248493</ymax></bndbox></object><object><name>Person</name><pose>Unspecified</pose><truncated>0</truncated><difficult>0</difficult><bndbox><xmin>967.1997439999999</xmin><ymin>228.496284</ymin><xmax>1024.0</xmax><ymax>353.369174</ymax></bndbox></object><object><name>Person</name><pose>Unspecified</pose><truncated>0</truncated><difficult>0</difficult><bndbox><xmin>1003.994112</xmin><ymin>208.28563100000002</ymin><xmax>1024.0</xmax><ymax>275.41360299999997</ymax></bndbox></object></annotation>