<annotation><filename>b31c7d3a91c084a2.jpg</filename><folder>images</folder><size><width>1024</width><height>576</height><depth>3</depth></size><object><name>Person</name><pose>Unspecified</pose><truncated>0</truncated><difficult>0</difficult><bndbox><xmin>52.402176000000004</xmin><ymin>132.742656</ymin><xmax>918.5822720000001</xmax><ymax>518.9074559999999</ymax></bndbox></object><object><name>Person</name><pose>Unspecified</pose><truncated>0</truncated><difficult>0</difficult><bndbox><xmin>690.435072</xmin><ymin>264.45888</ymin><xmax>1024.0</xmax><ymax>576.0</ymax></bndbox></object></annotation>