<annotation><filename>d21fc70bd9407f65.jpg</filename><folder>images</folder><size><width>1024</width><height>768</height><depth>3</depth></size><object><name>Person</name><pose>Unspecified</pose><truncated>0</truncated><difficult>0</difficult><bndbox><xmin>0.026624000000000002</xmin><ymin>216.824064</ymin><xmax>242.673664</xmax><ymax>486.185472</ymax></bndbox></object><object><name>Person</name><pose>Unspecified</pose><truncated>0</truncated><difficult>0</difficult><bndbox><xmin>5.062656</xmin><ymin>148.982784</ymin><xmax>1022.8224</xmax><ymax>767.925504</ymax></bndbox></object><object><name>Person</name><pose>Unspecified</pose><truncated>0</truncated><difficult>0</difficult><bndbox><xmin>272.748544</xmin><ymin>250.32345600000002</ymin><xmax>479.853568</xmax><ymax>459.52281600000003</ymax></bndbox></object><object><name>Person</name><pose>Unspecified</pose><truncated>0</truncated><difficult>0</difficult><bndbox><xmin>434.05824</xmin><ymin>195.631104</ymin><xmax>475.7524480000001</xmax><ymax>268.098816</ymax></bndbox></object><object><name>Person</name><pose>Unspecified</pose><truncated>0</truncated><difficult>0</difficult><bndbox><xmin>448.41164800000007</xmin><ymin>243.48672</ymin><xmax>552.305664</xmax><ymax>391.15699199999995</ymax></bndbox></object><object><name>Person</name><pose>Unspecified</pose><truncated>0</truncated><difficult>0</difficult><bndbox><xmin>487.37177599999995</xmin><ymin>251.006976</ymin><xmax>742.3232</xmax><ymax>508.74547200000006</ymax></bndbox></object><object><name>Person</name><pose>Unspecified</pose><truncated>0</truncated><difficult>0</difficult><bndbox><xmin>525.648896</xmin><ymin>183.32544000000001</ymin><xmax>602.8861440000001</xmax><ymax>315.954432</ymax></bndbox></object><object><name>Person</name><pose>Unspecified</pose><truncated>0</truncated><difficult>0</difficult><bndbox><xmin>548.7769599999999</xmin><ymin>263.835648</ymin><xmax>1024.0</xmax><ymax>767.3948160000001</ymax></bndbox></object><object><name>Person</name><pose>Unspecified</pose><truncated>0</truncated><difficult>0</difficult><bndbox><xmin>696.5268480000001</xmin><ymin>268.782336</ymin><xmax>786.067456</xmax><ymax>384.320256</ymax></bndbox></object><object><name>Person</name><pose>Unspecified</pose><truncated>0</truncated><difficult>0</difficult><bndbox><xmin>926.871552</xmin><ymin>271.51718400000004</ymin><xmax>1015.728128</xmax><ymax>437.645568</ymax></bndbox></object></annotation>