<annotation><filename>e6c4d78d08c3e3ce.jpg</filename><folder>images</folder><size><width>1024</width><height>768</height><depth>3</depth></size><object><name>Person</name><pose>Unspecified</pose><truncated>0</truncated><difficult>0</difficult><bndbox><xmin>2.5446400000000002</xmin><ymin>325.228032</ymin><xmax>203.078656</xmax><ymax>521.07648</ymax></bndbox></object><object><name>Person</name><pose>Unspecified</pose><truncated>0</truncated><difficult>0</difficult><bndbox><xmin>211.495936</xmin><ymin>346.7919360000001</ymin><xmax>260.425728</xmax><ymax>484.04582400000004</ymax></bndbox></object></annotation>