<annotation><filename>eefad9609b2e9edc.jpg</filename><folder>images</folder><size><width>1024</width><height>682</height><depth>3</depth></size><object><name>Person</name><pose>Unspecified</pose><truncated>0</truncated><difficult>0</difficult><bndbox><xmin>0.0</xmin><ymin>243.842962</ymin><xmax>92.350464</xmax><ymax>682.0</ymax></bndbox></object><object><name>Person</name><pose>Unspecified</pose><truncated>0</truncated><difficult>0</difficult><bndbox><xmin>140.342272</xmin><ymin>259.854958</ymin><xmax>219.09708799999999</xmax><ymax>530.820378</ymax></bndbox></object><object><name>Person</name><pose>Unspecified</pose><truncated>0</truncated><difficult>0</difficult><bndbox><xmin>201.869312</xmin><ymin>327.595972</ymin><xmax>231.40249599999999</xmax><ymax>508.650604</ymax></bndbox></object><object><name>Person</name><pose>Unspecified</pose><truncated>0</truncated><difficult>0</difficult><bndbox><xmin>221.55878399999997</xmin><ymin>192.113262</ymin><xmax>728.546304</xmax><ymax>541.905606</ymax></bndbox></object><object><name>Person</name><pose>Unspecified</pose><truncated>0</truncated><difficult>0</difficult><bndbox><xmin>351.99692799999997</xmin><ymin>236.453492</ymin><xmax>484.89676799999995</xmax><ymax>642.901622</ymax></bndbox></object><object><name>Person</name><pose>Unspecified</pose><truncated>0</truncated><difficult>0</difficult><bndbox><xmin>699.4831360000001</xmin><ymin>224.358904</ymin><xmax>820.891648</xmax><ymax>531.8188260000001</ymax></bndbox></object><object><name>Person</name><pose>Unspecified</pose><truncated>0</truncated><difficult>0</difficult><bndbox><xmin>823.298048</xmin><ymin>162.553336</ymin><xmax>1024.0</xmax><ymax>373.167894</ymax></bndbox></object><object><name>Person</name><pose>Unspecified</pose><truncated>0</truncated><difficult>0</difficult><bndbox><xmin>937.739264</xmin><ymin>171.17517999999998</ymin><xmax>1022.6483199999999</xmax><ymax>546.831692</ymax></bndbox></object></annotation>