<annotation><filename>f9ec641509f8f5a5.jpg</filename><folder>images</folder><size><width>1024</width><height>768</height><depth>3</depth></size><object><name>Person</name><pose>Unspecified</pose><truncated>0</truncated><difficult>0</difficult><bndbox><xmin>28.137472</xmin><ymin>413.96428799999995</ymin><xmax>100.182016</xmax><ymax>591.153408</ymax></bndbox></object><object><name>Person</name><pose>Unspecified</pose><truncated>0</truncated><difficult>0</difficult><bndbox><xmin>814.454784</xmin><ymin>542.677248</ymin><xmax>931.8789119999999</xmax><ymax>740.623872</ymax></bndbox></object></annotation>