<annotation><filename>fcf009c6e92826fc.jpg</filename><folder>images</folder><size><width>1024</width><height>921</height><depth>3</depth></size><object><name>Person</name><pose>Unspecified</pose><truncated>0</truncated><difficult>0</difficult><bndbox><xmin>753.3895679999999</xmin><ymin>81.58218</ymin><xmax>854.647808</xmax><ymax>338.43066</ymax></bndbox></object><object><name>Person</name><pose>Unspecified</pose><truncated>0</truncated><difficult>0</difficult><bndbox><xmin>792.904704</xmin><ymin>66.764211</ymin><xmax>913.921024</xmax><ymax>312.08729700000004</ymax></bndbox></object></annotation>